odoo9_addon_hr_payroll_cancel-9.0.1.0.0.99.dev2-py2.7-nspkg.pth
odoo9_addon_hr_payroll_cancel-9.0.1.0.0.99.dev2.dist-info/DESCRIPTION.rst
odoo9_addon_hr_payroll_cancel-9.0.1.0.0.99.dev2.dist-info/METADATA
odoo9_addon_hr_payroll_cancel-9.0.1.0.0.99.dev2.dist-info/RECORD
odoo9_addon_hr_payroll_cancel-9.0.1.0.0.99.dev2.dist-info/WHEEL
odoo9_addon_hr_payroll_cancel-9.0.1.0.0.99.dev2.dist-info/metadata.json
odoo9_addon_hr_payroll_cancel-9.0.1.0.0.99.dev2.dist-info/namespace_packages.txt
odoo9_addon_hr_payroll_cancel-9.0.1.0.0.99.dev2.dist-info/top_level.txt
odoo_addons/hr_payroll_cancel/README.rst
odoo_addons/hr_payroll_cancel/__init__.py
odoo_addons/hr_payroll_cancel/__openerp__.py
odoo_addons/hr_payroll_cancel/hooks.py
odoo_addons/hr_payroll_cancel/hr_payslip_workflow.xml
odoo_addons/hr_payroll_cancel/i18n/fr.po
odoo_addons/hr_payroll_cancel/i18n/hr_payroll_cancel.pot
odoo_addons/hr_payroll_cancel/i18n/sl.po
odoo_addons/hr_payroll_cancel/static/description/icon.png
odoo_addons/hr_payroll_cancel/views/hr_payslip_view.xml
